CHANGES.txt
MANIFEST.in
README.txt
setup.py
jinja2_alchemy_starter/__init__.py
jinja2_alchemy_starter.egg-info/PKG-INFO
jinja2_alchemy_starter.egg-info/SOURCES.txt
jinja2_alchemy_starter.egg-info/dependency_links.txt
jinja2_alchemy_starter.egg-info/entry_points.txt
jinja2_alchemy_starter.egg-info/not-zip-safe
jinja2_alchemy_starter.egg-info/requires.txt
jinja2_alchemy_starter.egg-info/top_level.txt
jinja2_alchemy_starter/scaffolds/__init__.py
jinja2_alchemy_starter/scaffolds/pyjinal_scaffold/CHANGES.txt_tmpl
jinja2_alchemy_starter/scaffolds/pyjinal_scaffold/MANIFEST.in_tmpl
jinja2_alchemy_starter/scaffolds/pyjinal_scaffold/README.txt_tmpl
jinja2_alchemy_starter/scaffolds/pyjinal_scaffold/development.ini_tmpl
jinja2_alchemy_starter/scaffolds/pyjinal_scaffold/message-extraction.ini_tmpl
jinja2_alchemy_starter/scaffolds/pyjinal_scaffold/setup.cfg_tmpl
jinja2_alchemy_starter/scaffolds/pyjinal_scaffold/setup.py_tmpl
jinja2_alchemy_starter/scaffolds/pyjinal_scaffold/+package+/__init__.py_tmpl
jinja2_alchemy_starter/scaffolds/pyjinal_scaffold/+package+/models.py
jinja2_alchemy_starter/scaffolds/pyjinal_scaffold/+package+/tests.py_tmpl
jinja2_alchemy_starter/scaffolds/pyjinal_scaffold/+package+/views.py_tmpl
jinja2_alchemy_starter/scaffolds/pyjinal_scaffold/+package+/locale/+package+.pot
jinja2_alchemy_starter/scaffolds/pyjinal_scaffold/+package+/locale/de/LC_MESSAGES/+package+.mo
jinja2_alchemy_starter/scaffolds/pyjinal_scaffold/+package+/locale/de/LC_MESSAGES/+package+.po
jinja2_alchemy_starter/scaffolds/pyjinal_scaffold/+package+/locale/fr/LC_MESSAGES/+package+.mo
jinja2_alchemy_starter/scaffolds/pyjinal_scaffold/+package+/locale/fr/LC_MESSAGES/+package+.po
jinja2_alchemy_starter/scaffolds/pyjinal_scaffold/+package+/static/logo.png
jinja2_alchemy_starter/scaffolds/pyjinal_scaffold/+package+/static/pylons.css
jinja2_alchemy_starter/scaffolds/pyjinal_scaffold/+package+/templates/mytemplate.jinja2