Metadata-Version: 1.0
Name: jinja2-alchemy-starter
Version: 0.3.1
Summary: Pyramid Scaffold for getting started with SQLAlchemy ORM and Jinja2 Templating Engine
Home-page: UNKNOWN
Author: Dheeraj Gupta
Author-email: dheeraj.gupta4@gmail.com
License: UNKNOWN
Keywords: pylons pyramid scaffolds
Platform: UNKNOWN
